[
  {
    "lat": 4.6029937452,
    "long": -74.0649908569,
    "floor": 7,
    "FID": 0,
    "area": -1
  },
  {
    "lat": 4.6029617250,
    "long": -74.0649489720,
    "floor": 7,
    "FID": 1,
    "area": -1,
    "bloque": "ML"
  },
  {
    "lat": 4.6030279887,
    "long": -74.0648769533,
    "floor": 7,
    "FID": 2,
    "area": -1,
    "bloque": "ML"
  },
  {
    "lat": 4.6027868263,
    "long": -74.0649678822,
    "floor": 7,
    "FID": 3,
    "area": -1,
    "bloque": "ML"
  },
  {
    "lat": 4.6027614672,
    "long": -74.0646870193,
    "floor": 7,
    "FID": 4,
    "area": -1,
    "bloque": "ML"
  },
  {
    "lat": 4.6028536585,
    "long": -74.0650521922,
    "floor": 7,
    "FID": 5,
    "area": -1,
    "bloque": "ML"
  },
  {
    "lat": 4.6027929231,
    "long": -74.0647315889,
    "floor": 7,
    "FID": 6,
    "area": -1,
    "bloque": "ML"
  },
  {
    "lat": 4.6028605642,
    "long": -74.0648150900,
    "floor": 7,
    "FID": 7,
    "area": -1,
    "bloque": "ML"
  },
  {
    "lat": 4.6029193558,
    "long": -74.0648350498,
    "floor": 7,
    "FID": 8,
    "area": -1,
    "bloque": "ML"
  },
  {
    "lat": 4.6029260123,
    "long": -74.0649038129,
    "floor": 7,
    "FID": 9,
    "area": -1,
    "bloque": "ML"
  },
  {
    "lat": 4.6030122114,
    "long": -74.0648930335,
    "floor": 7,
    "FID": 10,
    "area": -1,
    "bloque": "ML"
  },
  {
    "lat": 4.6028957698,
    "long": -74.0648580300,
    "floor": 7,
    "FID": 11,
    "area": -1,
    "bloque": "ML"
  },
  {
    "lat": 4.6029458257,
    "long": -74.0651120759,
    "floor": 7,
    "FID": 12,
    "area": -1,
    "bloque": "ML"
  },
  {
    "lat": 4.6029760069,
    "long": -74.0650834091,
    "floor": 7,
    "FID": 13,
    "area": -1,
    "bloque": "ML"
  },
  {
    "lat": 4.6030795542,
    "long": -74.0649792561,
    "floor": 7,
    "FID": 14,
    "area": -1,
    "bloque": "ML"
  },
  {
    "lat": 4.6028269405,
    "long": -74.0647735969,
    "floor": 7,
    "FID": 15,
    "area": -1,
    "bloque": "ML"
  },
  {
    "lat": 4.6029807233,
    "long": -74.0648512222,
    "floor": 7,
    "FID": 16,
    "area": -1,
    "bloque": "ML"
  },
  {
    "lat": 4.6028863026,
    "long": -74.0650976938,
    "floor": 7,
    "FID": 17,
    "area": -1,
    "bloque": "ML"
  },
  {
    "lat": 4.6028197867,
    "long": -74.0650091299,
    "floor": 7,
    "FID": 18,
    "area": -1,
    "bloque": "ML"
  },
  {
    "lat": 4.6027473980,
    "long": -74.0648531394,
    "floor": 7,
    "FID": 19,
    "area": -1,
    "bloque": "ML"
  },
  {
    "lat": 4.6030393134,
    "long": -74.0648656286,
    "floor": 7,
    "FID": 20,
    "area": -1,
    "bloque": "ML"
  },
  {
    "lat": 4.6030513773,
    "long": -74.0650074330,
    "floor": 7,
    "FID": 21,
    "area": -1,
    "bloque": "ML"
  },
  {
    "lat": 4.6027137922,
    "long": -74.0648101140,
    "floor": 7,
    "FID": 22,
    "area": -1,
    "bloque": "ML"
  },
  {
    "lat": 4.6029191210,
    "long": -74.0651396893,
    "floor": 7,
    "FID": 23,
    "area": -1,
    "bloque": "ML"
  },
  {
    "lat": 4.6028134105,
    "long": -74.0649391778,
    "floor": 7,
    "FID": 24,
    "area": -1,
    "bloque": "ML"
  },
  {
    "lat": 4.6029467238,
    "long": -74.0648076818,
    "floor": 7,
    "FID": 25,
    "area": -1,
    "bloque": "ML"
  },
  {
    "lat": 4.6027208317,
    "long": -74.0648803115,
    "floor": 7,
    "FID": 26,
    "area": -1,
    "bloque": "ML"
  },
  {
    "lat": 4.6026224231,
    "long": -74.0647503408,
    "floor": 7,
    "FID": 27,
    "area": -1,
    "bloque": "ML"
  },
  {
    "lat": 4.6026816551,
    "long": -74.0647668314,
    "floor": 7,
    "FID": 28,
    "area": -1,
    "bloque": "ML"
  },
  {
    "lat": 4.6028810157,
    "long": -74.0650257436,
    "floor": 7,
    "FID": 29,
    "area": -1,
    "bloque": "ML"
  },
  {
    "lat": 4.6027822945,
    "long": -74.0648997203,
    "floor": 7,
    "FID": 30,
    "area": -1,
    "bloque": "ML"
  },
  {
    "lat": 4.6029131529,
    "long": -74.0650690262,
    "floor": 7,
    "FID": 31,
    "area": -1,
    "bloque": "ML"
  },
  {
    "lat": 4.6031061241,
    "long": -74.0649517775,
    "floor": 7,
    "FID": 32,
    "area": -1,
    "bloque": "ML"
  },
  {
    "lat": 4.6026886981,
    "long": -74.0648367225,
    "floor": 7,
    "FID": 33,
    "area": -1,
    "bloque": "ML"
  },
  {
    "lat": 4.6027114534,
    "long": -74.0647367302,
    "floor": 7,
    "FID": 34,
    "area": -1,
    "bloque": "ML"
  },
  {
    "lat": 4.6030476831,
    "long": -74.0649360104,
    "floor": 7,
    "FID": 35,
    "area": -1,
    "bloque": "ML"
  },
  {
    "lat": 4.6030731852,
    "long": -74.0649086909,
    "floor": 7,
    "FID": 36,
    "area": -1,
    "bloque": "ML"
  },
  {
    "lat": 4.6026560289,
    "long": -74.0647933663,
    "floor": 7,
    "FID": 37,
    "area": -1,
    "bloque": "ML"
  },
  {
    "lat": 4.6030255209,
    "long": -74.0650308662,
    "floor": 7,
    "FID": 38,
    "area": -1,
    "bloque": "ML"
  },
  {
    "lat": 4.6028155076,
    "long": -74.0646347962,
    "floor": 7,
    "FID": 39,
    "area": -1,
    "bloque": "ML"
  },
  {
    "lat": 4.6027757735,
    "long": -74.0645803315,
    "floor": 7,
    "FID": 40,
    "area": -1,
    "bloque": "ML"
  },
  {
    "lat": 4.6028489822,
    "long": -74.0646776500,
    "floor": 7,
    "FID": 41,
    "area": -1,
    "bloque": "ML"
  },
  {
    "lat": 4.6028801899,
    "long": -74.0647206503,
    "floor": 7,
    "FID": 42,
    "area": -1,
    "bloque": "ML"
  },
  {
    "lat": 4.6029124511,
    "long": -74.0647647175,
    "floor": 7,
    "FID": 43,
    "area": -1,
    "bloque": "ML"
  },
  {
    "lat": 4.6029862059,
    "long": -74.0649178274,
    "floor": 7,
    "FID": 44,
    "area": -1,
    "bloque": "ML"
  },
  {
    "lat": 4.6030081307,
    "long": -74.0648204830,
    "floor": 7,
    "FID": 45,
    "area": -1,
    "bloque": "ML"
  },
  {
    "lat": 4.6029738437,
    "long": -74.0647787446,
    "floor": 7,
    "FID": 46,
    "area": -1,
    "bloque": "ML"
  },
  {
    "lat": 4.6029409120,
    "long": -74.0647350450,
    "floor": 7,
    "FID": 47,
    "area": -1,
    "bloque": "ML"
  },
  {
    "lat": 4.6029081080,
    "long": -74.0646918236,
    "floor": 7,
    "FID": 48,
    "area": -1,
    "bloque": "ML"
  },
  {
    "lat": 4.6028754172,
    "long": -74.0646503063,
    "floor": 7,
    "FID": 49,
    "area": -1,
    "bloque": "ML"
  },
  {
    "lat": 4.6028418186,
    "long": -74.0646066679,
    "floor": 7,
    "FID": 50,
    "area": -1,
    "bloque": "ML"
  },
  {
    "lat": 4.6029101292,
    "long": -74.0649972359,
    "floor": 7,
    "FID": 51,
    "area": -1,
    "bloque": "ML"
  },
  {
    "lat": 4.6028433329,
    "long": -74.0649098612,
    "floor": 7,
    "FID": 52,
    "area": -1,
    "bloque": "ML"
  },
  {
    "lat": 4.6027773239,
    "long": -74.0648235163,
    "floor": 7,
    "FID": 53,
    "area": -1,
    "bloque": "ML"
  },
  {
    "lat": 4.6028527014,
    "long": -74.0647469273,
    "floor": 7,
    "FID": 54,
    "area": -1,
    "bloque": "ML"
  },
  {
    "lat": 4.6027846451,
    "long": -74.0646647501,
    "floor": 7,
    "FID": 55,
    "area": -1,
    "bloque": "ML"
  },
  {
    "lat": 4.6028471367,
    "long": -74.0649832943,
    "floor": 7,
    "FID": 56,
    "area": -1,
    "bloque": "ML"
  },
]